{"ezera iela 1 - 1":{"address":"Ezera iela 1 - 1","city":"Stoļerova","zip":"LV-4642"},"ezera iela 1 - 2":{"address":"Ezera iela 1 - 2","city":"Stoļerova","zip":"LV-4642"},"ezera iela 1 - 3":{"address":"Ezera iela 1 - 3","city":"Stoļerova","zip":"LV-4642"},"ezera iela 1 - 4":{"address":"Ezera iela 1 - 4","city":"Stoļerova","zip":"LV-4642"},"ezera iela 1 - 5":{"address":"Ezera iela 1 - 5","city":"Stoļerova","zip":"LV-4642"},"ezera iela 1 - 6":{"address":"Ezera iela 1 - 6","city":"Stoļerova","zip":"LV-4642"},"ezera iela 1 - 7":{"address":"Ezera iela 1 - 7","city":"Stoļerova","zip":"LV-4642"},"ezera iela 1 - 8":{"address":"Ezera iela 1 - 8","city":"Stoļerova","zip":"LV-4642"},"ezera iela 1 - 9":{"address":"Ezera iela 1 - 9","city":"Stoļerova","zip":"LV-4642"},"ezera iela 1 - 10":{"address":"Ezera iela 1 - 10","city":"Stoļerova","zip":"LV-4642"},"ezera iela 1 - 11":{"address":"Ezera iela 1 - 11","city":"Stoļerova","zip":"LV-4642"},"ezera iela 1 - 12":{"address":"Ezera iela 1 - 12","city":"Stoļerova","zip":"LV-4642"},"ezera iela 2 - 1":{"address":"Ezera iela 2 - 1","city":"Stoļerova","zip":"LV-4642"},"ezera iela 2 - 2":{"address":"Ezera iela 2 - 2","city":"Stoļerova","zip":"LV-4642"},"ezera iela 2 - 3":{"address":"Ezera iela 2 - 3","city":"Stoļerova","zip":"LV-4642"},"ezera iela 2 - 4":{"address":"Ezera iela 2 - 4","city":"Stoļerova","zip":"LV-4642"},"ezera iela 2 - 5":{"address":"Ezera iela 2 - 5","city":"Stoļerova","zip":"LV-4642"},"ezera iela 2 - 6":{"address":"Ezera iela 2 - 6","city":"Stoļerova","zip":"LV-4642"},"ezera iela 2 - 7":{"address":"Ezera iela 2 - 7","city":"Stoļerova","zip":"LV-4642"},"ezera iela 2 - 8":{"address":"Ezera iela 2 - 8","city":"Stoļerova","zip":"LV-4642"},"ezera iela 2 - 9":{"address":"Ezera iela 2 - 9","city":"Stoļerova","zip":"LV-4642"},"ezera iela 2 - 10":{"address":"Ezera iela 2 - 10","city":"Stoļerova","zip":"LV-4642"},"ezera iela 2 - 11":{"address":"Ezera iela 2 - 11","city":"Stoļerova","zip":"LV-4642"},"ezera iela 2 - 12":{"address":"Ezera iela 2 - 12","city":"Stoļerova","zip":"LV-4642"}}