{"smiltis - 2":{"address":"Smiltis - 2","city":"Anna","zip":"LV-4341"},"smiltis - 1":{"address":"Smiltis - 1","city":"Anna","zip":"LV-4341"},"smiltis - 3":{"address":"Smiltis - 3","city":"Anna","zip":"LV-4341"},"smiltis - 4":{"address":"Smiltis - 4","city":"Anna","zip":"LV-4341"},"smiltis - 5":{"address":"Smiltis - 5","city":"Anna","zip":"LV-4341"},"smiltis - 6":{"address":"Smiltis - 6","city":"Anna","zip":"LV-4341"},"smiltis - 7":{"address":"Smiltis - 7","city":"Anna","zip":"LV-4341"},"smiltis - 10":{"address":"Smiltis - 10","city":"Anna","zip":"LV-4341"},"smiltis - 9":{"address":"Smiltis - 9","city":"Anna","zip":"LV-4341"},"smiltis - 8":{"address":"Smiltis - 8","city":"Anna","zip":"LV-4341"},"smiltis - 13":{"address":"Smiltis - 13","city":"Anna","zip":"LV-4341"},"smiltis - 11":{"address":"Smiltis - 11","city":"Anna","zip":"LV-4341"},"smiltis - 12":{"address":"Smiltis - 12","city":"Anna","zip":"LV-4341"},"smiltis":{"address":"Smiltis","city":"Slostovka","zip":"LV-5653"}}